adopy/__init__.py
adopy/base/__init__.py
adopy/base/_engine.py
adopy/base/_model.py
adopy/base/_task.py
adopy/functions/__init__.py
adopy/functions/_const.py
adopy/functions/_grid.py
adopy/functions/_utils.py
adopy/tasks/__init__.py
adopy/tasks/cra.py
adopy/tasks/dd.py
adopy/tasks/psi.py
adopy/types.py
adopy-0.4.1.dist-info/LICENSE
adopy-0.4.1.dist-info/WHEEL
adopy-0.4.1.dist-info/METADATA
adopy-0.4.1.dist-info/RECORD
