Metadata-Version: 2.1
Name: adopy
Version: 0.4.1
Summary: Adaptive Design Optimization on Experimental Tasks
Home-page: https://adopy.org
License: GPL-3.0+
Author: Jaeyeong Yang
Author-email: jaeyeong.yang1125@gmail.com
Requires-Python: >=3.6
Classifier: Development Status :: 4 - Beta
Classifier: Intended Audience :: Science/Research
Classifier: License :: OSI Approved :: GNU General Public License v3 or later (GPLv3+)
Classifier: Programming Language :: Python :: 3
Classifier: Programming Language :: Python :: 3 :: Only
Classifier: Programming Language :: Python :: 3.10
Classifier: Programming Language :: Python :: 3.6
Classifier: Programming Language :: Python :: 3.7
Classifier: Programming Language :: Python :: 3.8
Classifier: Programming Language :: Python :: 3.9
Provides-Extra: docs
Provides-Extra: test
Requires-Dist: codecov; extra == "test"
Requires-Dist: importlib_metadata; python_version < "3.8"
Requires-Dist: ipykernel; extra == "docs"
Requires-Dist: jupyterlab; extra == "docs"
Requires-Dist: matplotlib; extra == "docs"
Requires-Dist: nbsphinx; extra == "docs"
Requires-Dist: numpy
Requires-Dist: pandas
Requires-Dist: pytest (>=6.0); extra == "test"
Requires-Dist: pytest-cov; extra == "test"
Requires-Dist: recommonmark; extra == "docs"
Requires-Dist: scipy (>=1.0.0)
Requires-Dist: sphinx-autobuild; extra == "docs"
Requires-Dist: sphinx-issues; extra == "docs"
Requires-Dist: sphinx; extra == "docs"
Requires-Dist: sphinx_rtd_theme; extra == "docs"
Project-URL: Documentation, https://adopy.org
Project-URL: Repository, https://github.com/adopy/adopy
